Metadata-Version: 1.1
Name: django-notifications-latest
Version: 2.1.0
Summary: GitHub notifications alike app for Django.
Home-page: https://github.com/shamilbuzz/django-notifications
Author: django-notifications team
Author-email: yang@yangyubo.com
License: MIT
Keywords: django notifications github action event stream
Platform: UNKNOWN
Classifier: Development Status :: 5 - Production/Stable
Classifier: Environment :: Web Environment
Classifier: Framework :: Django
Classifier: Intended Audience :: Developers
Classifier: License :: OSI Approved :: BSD License
Classifier: Operating System :: OS Independent
Classifier: Framework :: Django
Classifier: Framework :: Django :: 1.10
Classifier: Framework :: Django :: 1.9
Classifier: Framework :: Django :: 1.8
Classifier: Framework :: Django :: 1.7
Classifier: Programming Language :: Python
Classifier: Programming Language :: Python :: 2
Classifier: Programming Language :: Python :: 2.7
Classifier: Programming Language :: Python :: 3
Classifier: Programming Language :: Python :: 3.3
Classifier: Programming Language :: Python :: 3.4
Classifier: Topic :: Utilities
